linkml_reference_validator/__init__.py
linkml_reference_validator/_version.py
linkml_reference_validator/models.py
linkml_reference_validator/cli/__init__.py
linkml_reference_validator/cli/cache.py
linkml_reference_validator/cli/repair.py
linkml_reference_validator/cli/shared.py
linkml_reference_validator/cli/validate.py
linkml_reference_validator/etl/__init__.py
linkml_reference_validator/etl/reference_fetcher.py
linkml_reference_validator/etl/text_extractor.py
linkml_reference_validator/plugins/REVIEW.md
linkml_reference_validator/plugins/__init__.py
linkml_reference_validator/plugins/reference_validation_plugin.py
linkml_reference_validator/validation/__init__.py
linkml_reference_validator/validation/fuzzy_text_utils.py
linkml_reference_validator/validation/repairer.py
linkml_reference_validator/validation/supporting_text_validator.py
linkml_reference_validator-0.1.3.dist-info/METADATA
linkml_reference_validator-0.1.3.dist-info/WHEEL
linkml_reference_validator-0.1.3.dist-info/entry_points.txt
linkml_reference_validator-0.1.3.dist-info/licenses/LICENSE
linkml_reference_validator-0.1.3.dist-info/RECORD
