Metadata-Version: 2.4
Name: linkml_reference_validator
Version: 0.1.3
Summary: Validation of supporting text from references and publications
Author-email: Chris Mungall <cjmungall@lbl.gov>
License-Expression: Apache-2.0
License-File: LICENSE
Requires-Python: <4.0,>=3.10
Requires-Dist: beautifulsoup4>=4.9.0
Requires-Dist: biopython>=1.80
Requires-Dist: linkml-runtime>=1.9.4
Requires-Dist: lxml>=4.9.0
Requires-Dist: pydantic>=2.0.0
Requires-Dist: rapidfuzz>=3.14.3
Requires-Dist: requests>=2.28.0
Requires-Dist: ruamel-yaml>=0.18.0
Requires-Dist: typer>=0.9.0
